LICENSE
README.md
setup.py
TrillerAPI/__init__.py
TrillerAPI/exceptions.py
TrillerAPI/user.py
TrillerAPI.egg-info/PKG-INFO
TrillerAPI.egg-info/SOURCES.txt
TrillerAPI.egg-info/dependency_links.txt
TrillerAPI.egg-info/requires.txt
TrillerAPI.egg-info/top_level.txt