Metadata-Version: 2.1
Name: TrillerAPI
Version: 0.0.1
Summary: The Unofficial Triller API Wrapper in Python 3.
Home-page: https://github.com/davidteather/triller-api
Author: David Teather
Author-email: contact.davidteather@gmail.com
License: MIT
Download-URL: https://github.com/davidteather/triller-api/tarball/main
Keywords: triller,api,triller-api,unofficial
Platform: UNKNOWN
Classifier: Development Status :: 3 - Alpha
Classifier: Intended Audience :: Developers
Classifier: Topic :: Software Development :: Build Tools
Classifier: License :: OSI Approved :: MIT License
Classifier: Programming Language :: Python :: 3.7
Classifier: Programming Language :: Python :: 3.8
Classifier: Programming Language :: Python :: 3.9
